[{"Grw": "W", "RadiusVis": "3000", "Nav": "1", "Hem": "S", "LongMin": "18", "LongMil": "177", "NoWptAsr": "", "Asr": "0", "VitLim": "0", "RadiusWpt": "200", "CodeWpt": "216", "lon": "-64.30295", "WPM": "0", "CodeB": "8765", "WPE": "0", "actif": "1", "LatMil": "911", "LatMin": "15", "Tpe": "0", "Tpc": "1", "NomWpt": "E1K0 ", "LatDeg": "31", "Tps": "0", "lat": "-31.2651833333", "NoWpt": "1", "CP": "1", "NbModif": "2", "LongDeg": "64", "CodeRoute": "138", "VitInter": "0", "Odometre": "1", "NoWptNav": "1", "radius": "200", "Tri2": "1"}, {"Grw": "W", "RadiusVis": "3000", "Nav": "1", "Hem": "S", "LongMin": "19", "LongMil": "279", "NoWptAsr": "", "Asr": "0", "VitLim": "0", "RadiusWpt": "200", "CodeWpt": "218", "lon": "-64.3213166667", "WPM": "0", "CodeB": "8765", "WPE": "0", "actif": "1", "LatMil": "685", "LatMin": "16", "Tpe": "0", "Tpc": "1", "NomWpt": "K7   ", "LatDeg": "31", "Tps": "0", "lat": "-31.2780833333", "NoWpt": "2", "CP": "1", "NbModif": "2", "LongDeg": "64", "CodeRoute": "138", "VitInter": "0", "Odometre": "7240", "NoWptNav": "2", "radius": "200", "Tri2": "2"}, {"Grw": "W", "RadiusVis": "3000", "Nav": "1", "Hem": "S", "LongMin": "19", "LongMil": "940", "NoWptAsr": "", "Asr": "0", "VitLim": "0", "RadiusWpt": "200", "CodeWpt": "220", "lon": "-64.3323333333", "WPM": "0", "CodeB": "8765", "WPE": "0", "actif": "1", "LatMil": "943", "LatMin": "15", "Tpe": "0", "Tpc": "1", "NomWpt": "DSS1 ", "LatDeg": "31", "Tps": "0", "lat": "-31.2657166667", "NoWpt": "3", "CP": "1", "NbModif": "2", "LongDeg": "64", "CodeRoute": "138", "VitInter": "0", "Odometre": "1", "NoWptNav": "3", "radius": "200", "Tri2": "3"}, {"Grw": "W", "RadiusVis": "3000", "Nav": "1", "Hem": "S", "LongMin": "27", "LongMil": "622", "NoWptAsr": "", "Asr": "0", "VitLim": "0", "RadiusWpt": "90", "CodeWpt": "222", "lon": "-64.4603666667", "WPM": "1", "CodeB": "8765", "WPE": "0", "actif": "1", "LatMil": "393", "LatMin": "13", "Tpe": "0", "Tpc": "1", "NomWpt": "CP1DZ", "LatDeg": "31", "Tps": "0", "lat": "-31.2232166667", "NoWpt": "4", "CP": "1", "NbModif": "2", "LongDeg": "64", "CodeRoute": "138", "VitInter": "30", "Odometre": "22200", "NoWptNav": "4", "radius": "90", "Tri2": "4"}, {"Grw": "W", "RadiusVis": "3000", "Nav": "1", "Hem": "S", "LongMin": "28", "LongMil": "689", "NoWptAsr": "", "Asr": "0", "VitLim": "0", "RadiusWpt": "90", "CodeWpt": "224", "lon": "-64.47815", "WPM": "1", "CodeB": "8765", "WPE": "1", "actif": "1", "LatMil": "266", "LatMin": "13", "Tpe": "0", "Tpc": "1", "NomWpt": "FZ24 ", "LatDeg": "31", "Tps": "0", "lat": "-31.2211", "NoWpt": "5", "CP": "1", "NbModif": "2", "LongDeg": "64", "CodeRoute": "138", "VitInter": "0", "Odometre": "24160", "NoWptNav": "5", "radius": "90", "Tri2": "5"}, {"Grw": "W", "RadiusVis": "3000", "Nav": "1", "Hem": "S", "LongMin": "28", "LongMil": "865", "NoWptAsr": "", "Asr": "0", "VitLim": "0", "RadiusWpt": "90", "CodeWpt": "226", "lon": "-64.4810833333", "WPM": "1", "CodeB": "8765", "WPE": "0", "actif": "1", "LatMil": "95", "LatMin": "12", "Tpe": "0", "Tpc": "1", "NomWpt": "DZ26 ", "LatDeg": "31", "Tps": "0", "lat": "-31.2158333333", "NoWpt": "6", "CP": "1", "NbModif": "2", "LongDeg": "64", "CodeRoute": "138", "VitInter": "30", "Odometre": "26950", "NoWptNav": "6", "radius": "90", "Tri2": "6"}, {"Grw": "W", "RadiusVis": "3000", "Nav": "1", "Hem": "S", "LongMin": "28", "LongMil": "727", "NoWptAsr": "", "Asr": "0", "VitLim": "0", "RadiusWpt": "90", "CodeWpt": "228", "lon": "-64.4787833333", "WPM": "1", "CodeB": "8765", "WPE": "1", "actif": "1", "LatMil": "603", "LatMin": "11", "Tpe": "0", "Tpc": "1", "NomWpt": "FZ28 ", "LatDeg": "31", "Tps": "0", "lat": "-31.1933833333", "NoWpt": "7", "CP": "1", "NbModif": "2", "LongDeg": "64", "CodeRoute": "138", "VitInter": "0", "Odometre": "28130", "NoWptNav": "7", "radius": "90", "Tri2": "7"}, {"Grw": "W", "RadiusVis": "3000", "Nav": "1", "Hem": "S", "LongMin": "38", "LongMil": "940", "NoWptAsr": "", "Asr": "0", "VitLim": "0", "RadiusWpt": "200", "CodeWpt": "230", "lon": "-64.649", "WPM": "1", "CodeB": "8765", "WPE": "0", "actif": "1", "LatMil": "633", "LatMin": "0", "Tpe": "0", "Tpc": "1", "NomWpt": "K60  ", "LatDeg": "31", "Tps": "0", "lat": "-31.01055", "NoWpt": "8", "CP": "1", "NbModif": "2", "LongDeg": "64", "CodeRoute": "138", "VitInter": "0", "Odometre": "60280", "NoWptNav": "8", "radius": "200", "Tri2": "8"}, {"Grw": "W", "RadiusVis": "3000", "Nav": "1", "Hem": "S", "LongMin": "39", "LongMil": "35", "NoWptAsr": "", "Asr": "0", "VitLim": "0", "RadiusWpt": "200", "CodeWpt": "232", "lon": "-64.6558333333", "WPM": "1", "CodeB": "8765", "WPE": "0", "actif": "1", "LatMil": "960", "LatMin": "50", "Tpe": "0", "Tpc": "1", "NomWpt": "K87  ", "LatDeg": "30", "Tps": "0", "lat": "-30.8493333333", "NoWpt": "9", "CP": "1", "NbModif": "2", "LongDeg": "64", "CodeRoute": "138", "VitInter": "0", "Odometre": "87700", "NoWptNav": "9", "radius": "200", "Tri2": "9"}, {"Grw": "W", "RadiusVis": "3000", "Nav": "1", "Hem": "S", "LongMin": "43", "LongMil": "959", "NoWptAsr": "", "Asr": "0", "VitLim": "0", "RadiusWpt": "90", "CodeWpt": "234", "lon": "-64.73265", "WPM": "1", "CodeB": "8765", "WPE": "0", "actif": "1", "LatMil": "167", "LatMin": "55", "Tpe": "0", "Tpc": "1", "NomWpt": "DZ107", "LatDeg": "30", "Tps": "0", "lat": "-30.91945", "NoWpt": "10", "CP": "1", "NbModif": "2", "LongDeg": "64", "CodeRoute": "138", "VitInter": "30", "Odometre": "107790", "NoWptNav": "10", "radius": "90", "Tri2": "10"}, {"Grw": "W", "RadiusVis": "3000", "Nav": "1", "Hem": "S", "LongMin": "44", "LongMil": "208", "NoWptAsr": "", "Asr": "0", "VitLim": "0", "RadiusWpt": "90", "CodeWpt": "236", "lon": "-64.7368", "WPM": "1", "CodeB": "8765", "WPE": "1", "actif": "1", "LatMil": "907", "LatMin": "54", "Tpe": "0", "Tpc": "1", "NomWpt": "FZ108", "LatDeg": "30", "Tps": "0", "lat": "-30.9151166667", "NoWpt": "11", "CP": "1", "NbModif": "2", "LongDeg": "64", "CodeRoute": "138", "VitInter": "0", "Odometre": "108580", "NoWptNav": "11", "radius": "90", "Tri2": "11"}, {"Grw": "W", "RadiusVis": "3000", "Nav": "1", "Hem": "S", "LongMin": "46", "LongMil": "5", "NoWptAsr": "", "Asr": "0", "VitLim": "0", "RadiusWpt": "90", "CodeWpt": "238", "lon": "-64.775", "WPM": "1", "CodeB": "8765", "WPE": "0", "actif": "1", "LatMil": "426", "LatMin": "56", "Tpe": "0", "Tpc": "1", "NomWpt": "DZ112", "LatDeg": "30", "Tps": "0", "lat": "-30.9404333333", "NoWpt": "12", "CP": "1", "NbModif": "2", "LongDeg": "64", "CodeRoute": "138", "VitInter": "30", "Odometre": "112950", "NoWptNav": "12", "radius": "90", "Tri2": "12"}, {"Grw": "W", "RadiusVis": "3000", "Nav": "1", "Hem": "S", "LongMin": "46", "LongMil": "173", "NoWptAsr": "", "Asr": "0", "VitLim": "0", "RadiusWpt": "90", "CodeWpt": "240", "lon": "-64.76955", "WPM": "1", "CodeB": "8765", "WPE": "1", "actif": "1", "LatMil": "599", "LatMin": "56", "Tpe": "0", "Tpc": "1", "NomWpt": "FZ113", "LatDeg": "30", "Tps": "0", "lat": "-30.9433166667", "NoWpt": "13", "CP": "1", "NbModif": "2", "LongDeg": "64", "CodeRoute": "138", "VitInter": "0", "Odometre": "113210", "NoWptNav": "13", "radius": "90", "Tri2": "13"}, {"Grw": "W", "RadiusVis": "3000", "Nav": "1", "Hem": "S", "LongMin": "58", "LongMil": "710", "NoWptAsr": "", "Asr": "0", "VitLim": "0", "RadiusWpt": "200", "CodeWpt": "242", "lon": "-64.9785", "WPM": "0", "CodeB": "8765", "WPE": "0", "actif": "1", "LatMil": "82", "LatMin": "51", "Tpe": "0", "Tpc": "1", "NomWpt": "INEUT", "LatDeg": "30", "Tps": "0", "lat": "-30.8636666667", "NoWpt": "14", "CP": "1", "NbModif": "2", "LongDeg": "64", "CodeRoute": "138", "VitInter": "0", "Odometre": "142260", "NoWptNav": "14", "radius": "200", "Tri2": "14"}, {"Grw": "W", "RadiusVis": "3000", "Nav": "1", "Hem": "S", "LongMin": "59", "LongMil": "583", "NoWptAsr": "", "Asr": "0", "VitLim": "0", "RadiusWpt": "200", "CodeWpt": "244", "lon": "-64.99305", "WPM": "0", "CodeB": "8765", "WPE": "0", "actif": "1", "LatMil": "206", "LatMin": "51", "Tpe": "0", "Tpc": "1", "NomWpt": "K143 ", "LatDeg": "30", "Tps": "0", "lat": "-30.8534333333", "NoWpt": "15", "CP": "1", "NbModif": "2", "LongDeg": "64", "CodeRoute": "138", "VitInter": "0", "Odometre": "143850", "NoWptNav": "15", "radius": "200", "Tri2": "15"}, {"Grw": "W", "RadiusVis": "3000", "Nav": "1", "Hem": "S", "LongMin": "13", "LongMil": "965", "NoWptAsr": "", "Asr": "0", "VitLim": "0", "RadiusWpt": "200", "CodeWpt": "246", "lon": "-65.23275", "WPM": "0", "CodeB": "8765", "WPE": "0", "actif": "1", "LatMil": "897", "LatMin": "44", "Tpe": "0", "Tpc": "1", "NomWpt": "K170 ", "LatDeg": "30", "Tps": "0", "lat": "-30.7482833333", "NoWpt": "16", "CP": "1", "NbModif": "2", "LongDeg": "65", "CodeRoute": "138", "VitInter": "0", "Odometre": "170360", "NoWptNav": "16", "radius": "200", "Tri2": "16"}, {"Grw": "W", "RadiusVis": "3000", "Nav": "1", "Hem": "S", "LongMin": "14", "LongMil": "528", "NoWptAsr": "", "Asr": "0", "VitLim": "0", "RadiusWpt": "200", "CodeWpt": "248", "lon": "-65.2421333333", "WPM": "0", "CodeB": "8765", "WPE": "0", "actif": "1", "LatMil": "489", "LatMin": "45", "Tpe": "0", "Tpc": "1", "NomWpt": "FNEUT", "LatDeg": "30", "Tps": "0", "lat": "-30.75815", "NoWpt": "17", "CP": "1", "NbModif": "2", "LongDeg": "65", "CodeRoute": "138", "VitInter": "0", "Odometre": "172190", "NoWptNav": "17", "radius": "200", "Tri2": "17"}, {"Grw": "W", "RadiusVis": "3000", "Nav": "1", "Hem": "S", "LongMin": "21", "LongMil": "787", "NoWptAsr": "", "Asr": "0", "VitLim": "0", "RadiusWpt": "90", "CodeWpt": "250", "lon": "-65.3631166667", "WPM": "1", "CodeB": "8765", "WPE": "0", "actif": "1", "LatMil": "975", "LatMin": "50", "Tpe": "0", "Tpc": "1", "NomWpt": "DZ190", "LatDeg": "30", "Tps": "0", "lat": "-30.8495833333", "NoWpt": "18", "CP": "1", "NbModif": "2", "LongDeg": "65", "CodeRoute": "138", "VitInter": "30", "Odometre": "190560", "NoWptNav": "18", "radius": "90", "Tri2": "18"}, {"Grw": "W", "RadiusVis": "3000", "Nav": "1", "Hem": "S", "LongMin": "21", "LongMil": "990", "NoWptAsr": "", "Asr": "0", "VitLim": "0", "RadiusWpt": "90", "CodeWpt": "252", "lon": "-65.3665", "WPM": "1", "CodeB": "8765", "WPE": "1", "actif": "1", "LatMil": "350", "LatMin": "51", "Tpe": "0", "Tpc": "1", "NomWpt": "FZ191", "LatDeg": "30", "Tps": "0", "lat": "-30.8558333333", "NoWpt": "19", "CP": "1", "NbModif": "2", "LongDeg": "65", "CodeRoute": "138", "VitInter": "0", "Odometre": "191360", "NoWptNav": "19", "radius": "90", "Tri2": "19"}, {"Grw": "W", "RadiusVis": "3000", "Nav": "1", "Hem": "S", "LongMin": "21", "LongMil": "802", "NoWptAsr": "", "Asr": "0", "VitLim": "0", "RadiusWpt": "90", "CodeWpt": "254", "lon": "-65.3633666667", "WPM": "1", "CodeB": "8765", "WPE": "0", "actif": "1", "LatMil": "382", "LatMin": "0", "Tpe": "0", "Tpc": "1", "NomWpt": "DZ210", "LatDeg": "31", "Tps": "0", "lat": "-31.0063666667", "NoWpt": "20", "CP": "1", "NbModif": "2", "LongDeg": "65", "CodeRoute": "138", "VitInter": "30", "Odometre": "210030", "NoWptNav": "20", "radius": "90", "Tri2": "20"}, {"Grw": "W", "RadiusVis": "3000", "Nav": "1", "Hem": "S", "LongMin": "21", "LongMil": "765", "NoWptAsr": "", "Asr": "0", "VitLim": "0", "RadiusWpt": "90", "CodeWpt": "256", "lon": "-65.36275", "WPM": "1", "CodeB": "8765", "WPE": "1", "actif": "1", "LatMil": "738", "LatMin": "0", "Tpe": "0", "Tpc": "1", "NomWpt": "FZ210", "LatDeg": "31", "Tps": "0", "lat": "-31.0123", "NoWpt": "21", "CP": "1", "NbModif": "2", "LongDeg": "65", "CodeRoute": "138", "VitInter": "0", "Odometre": "210720", "NoWptNav": "21", "radius": "90", "Tri2": "21"}, {"Grw": "W", "RadiusVis": "3000", "Nav": "1", "Hem": "S", "LongMin": "20", "LongMil": "898", "NoWptAsr": "", "Asr": "0", "VitLim": "0", "RadiusWpt": "90", "CodeWpt": "258", "lon": "-65.3483", "WPM": "1", "CodeB": "8765", "WPE": "0", "actif": "1", "LatMil": "378", "LatMin": "4", "Tpe": "0", "Tpc": "1", "NomWpt": "DZ218", "LatDeg": "31", "Tps": "0", "lat": "-31.0729666667", "NoWpt": "22", "CP": "1", "NbModif": "2", "LongDeg": "65", "CodeRoute": "138", "VitInter": "30", "Odometre": "218170", "NoWptNav": "22", "radius": "90", "Tri2": "22"}, {"Grw": "W", "RadiusVis": "3000", "Nav": "1", "Hem": "S", "LongMin": "20", "LongMil": "907", "NoWptAsr": "", "Asr": "0", "VitLim": "0", "RadiusWpt": "90", "CodeWpt": "260", "lon": "-65.34845", "WPM": "1", "CodeB": "8765", "WPE": "1", "actif": "1", "LatMil": "630", "LatMin": "4", "Tpe": "0", "Tpc": "1", "NomWpt": "FZ218", "LatDeg": "31", "Tps": "0", "lat": "-31.0771666667", "NoWpt": "23", "CP": "1", "NbModif": "2", "LongDeg": "65", "CodeRoute": "138", "VitInter": "0", "Odometre": "218530", "NoWptNav": "23", "radius": "90", "Tri2": "23"}, {"Grw": "W", "RadiusVis": "3000", "Nav": "1", "Hem": "S", "LongMin": "17", "LongMil": "266", "NoWptAsr": "", "Asr": "0", "VitLim": "0", "RadiusWpt": "200", "CodeWpt": "262", "lon": "-65.2877666667", "WPM": "1", "CodeB": "8765", "WPE": "0", "actif": "1", "LatMil": "489", "LatMin": "22", "Tpe": "0", "Tpc": "1", "NomWpt": "K265 ", "LatDeg": "31", "Tps": "0", "lat": "-31.3748166667", "NoWpt": "24", "CP": "1", "NbModif": "2", "LongDeg": "65", "CodeRoute": "138", "VitInter": "0", "Odometre": "265680", "NoWptNav": "24", "radius": "200", "Tri2": "24"}, {"Grw": "W", "RadiusVis": "3000", "Nav": "1", "Hem": "S", "LongMin": "4", "LongMil": "797", "NoWptAsr": "", "Asr": "0", "VitLim": "0", "RadiusWpt": "200", "CodeWpt": "264", "lon": "-65.07995", "WPM": "1", "CodeB": "8765", "WPE": "0", "actif": "1", "LatMil": "773", "LatMin": "20", "Tpe": "0", "Tpc": "1", "NomWpt": "CP2  ", "LatDeg": "31", "Tps": "0", "lat": "-31.3462166667", "NoWpt": "25", "CP": "1", "NbModif": "2", "LongDeg": "65", "CodeRoute": "138", "VitInter": "0", "Odometre": "285610", "NoWptNav": "25", "radius": "200", "Tri2": "25"}, {"Grw": "W", "RadiusVis": "3000", "Nav": "1", "Hem": "S", "LongMin": "58", "LongMil": "980", "NoWptAsr": "", "Asr": "0", "VitLim": "0", "RadiusWpt": "90", "CodeWpt": "266", "lon": "-64.983", "WPM": "1", "CodeB": "8765", "WPE": "0", "actif": "1", "LatMil": "464", "LatMin": "21", "Tpe": "0", "Tpc": "1", "NomWpt": "DZ297", "LatDeg": "31", "Tps": "0", "lat": "-31.3577333333", "NoWpt": "26", "CP": "1", "NbModif": "2", "LongDeg": "64", "CodeRoute": "138", "VitInter": "30", "Odometre": "297160", "NoWptNav": "26", "radius": "90", "Tri2": "26"}, {"Grw": "W", "RadiusVis": "3000", "Nav": "1", "Hem": "S", "LongMin": "58", "LongMil": "575", "NoWptAsr": "", "Asr": "0", "VitLim": "0", "RadiusWpt": "90", "CodeWpt": "268", "lon": "-64.97625", "WPM": "1", "CodeB": "8765", "WPE": "1", "actif": "1", "LatMil": "120", "LatMin": "21", "Tpe": "0", "Tpc": "1", "NomWpt": "FZ298", "LatDeg": "31", "Tps": "0", "lat": "-31.352", "NoWpt": "27", "CP": "1", "NbModif": "2", "LongDeg": "64", "CodeRoute": "138", "VitInter": "0", "Odometre": "298410", "NoWptNav": "27", "radius": "90", "Tri2": "27"}, {"Grw": "W", "RadiusVis": "3000", "Nav": "1", "Hem": "S", "LongMin": "57", "LongMil": "138", "NoWptAsr": "", "Asr": "0", "VitLim": "0", "RadiusWpt": "200", "CodeWpt": "270", "lon": "-64.9523", "WPM": "1", "CodeB": "8765", "WPE": "0", "actif": "1", "LatMil": "736", "LatMin": "17", "Tpe": "0", "Tpc": "1", "NomWpt": "K306 ", "LatDeg": "31", "Tps": "0", "lat": "-31.2956", "NoWpt": "28", "CP": "1", "NbModif": "2", "LongDeg": "64", "CodeRoute": "138", "VitInter": "0", "Odometre": "306850", "NoWptNav": "28", "radius": "200", "Tri2": "28"}, {"Grw": "W", "RadiusVis": "3000", "Nav": "1", "Hem": "S", "LongMin": "55", "LongMil": "403", "NoWptAsr": "", "Asr": "0", "VitLim": "0", "RadiusWpt": "200", "CodeWpt": "272", "lon": "-64.9233833333", "WPM": "1", "CodeB": "8765", "WPE": "0", "actif": "1", "LatMil": "116", "LatMin": "13", "Tpe": "0", "Tpc": "1", "NomWpt": "K317 ", "LatDeg": "31", "Tps": "0", "lat": "-31.2186", "NoWpt": "29", "CP": "1", "NbModif": "2", "LongDeg": "64", "CodeRoute": "138", "VitInter": "0", "Odometre": "317910", "NoWptNav": "29", "radius": "200", "Tri2": "29"}, {"Grw": "W", "RadiusVis": "3000", "Nav": "1", "Hem": "S", "LongMin": "50", "LongMil": "783", "NoWptAsr": "", "Asr": "0", "VitLim": "0", "RadiusWpt": "200", "CodeWpt": "274", "lon": "-64.8463833333", "WPM": "1", "CodeB": "8765", "WPE": "0", "actif": "1", "LatMil": "974", "LatMin": "17", "Tpe": "0", "Tpc": "1", "NomWpt": "K334 ", "LatDeg": "31", "Tps": "0", "lat": "-31.2995666667", "NoWpt": "30", "CP": "1", "NbModif": "2", "LongDeg": "64", "CodeRoute": "138", "VitInter": "0", "Odometre": "334680", "NoWptNav": "30", "radius": "200", "Tri2": "30"}, {"Grw": "W", "RadiusVis": "3000", "Nav": "1", "Hem": "S", "LongMin": "48", "LongMil": "57", "NoWptAsr": "", "Asr": "0", "VitLim": "0", "RadiusWpt": "200", "CodeWpt": "276", "lon": "-64.8095", "WPM": "1", "CodeB": "8765", "WPE": "0", "actif": "1", "LatMil": "613", "LatMin": "7", "Tpe": "0", "Tpc": "1", "NomWpt": "K362 ", "LatDeg": "31", "Tps": "0", "lat": "-31.1268833333", "NoWpt": "31", "CP": "1", "NbModif": "2", "LongDeg": "64", "CodeRoute": "138", "VitInter": "0", "Odometre": "362490", "NoWptNav": "31", "radius": "200", "Tri2": "31"}, {"Grw": "W", "RadiusVis": "3000", "Nav": "1", "Hem": "S", "LongMin": "31", "LongMil": "132", "NoWptAsr": "", "Asr": "0", "VitLim": "0", "RadiusWpt": "200", "CodeWpt": "278", "lon": "-64.5188666667", "WPM": "0", "CodeB": "8765", "WPE": "0", "actif": "1", "LatMil": "322", "LatMin": "5", "Tpe": "0", "Tpc": "1", "NomWpt": "ASS 1", "LatDeg": "31", "Tps": "0", "lat": "-31.0887", "NoWpt": "32", "CP": "1", "NbModif": "2", "LongDeg": "64", "CodeRoute": "138", "VitInter": "0", "Odometre": "1", "NoWptNav": "32", "radius": "200", "Tri2": "32"}, {"Grw": "W", "RadiusVis": "3000", "Nav": "1", "Hem": "S", "LongMin": "30", "LongMil": "96", "NoWptAsr": "", "Asr": "0", "VitLim": "0", "RadiusWpt": "200", "CodeWpt": "280", "lon": "-64.516", "WPM": "0", "CodeB": "8765", "WPE": "0", "actif": "1", "LatMil": "342", "LatMin": "5", "Tpe": "0", "Tpc": "1", "NomWpt": "K1   ", "LatDeg": "31", "Tps": "0", "lat": "-31.0890333333", "NoWpt": "33", "CP": "1", "NbModif": "2", "LongDeg": "64", "CodeRoute": "138", "VitInter": "0", "Odometre": "1980", "NoWptNav": "33", "radius": "200", "Tri2": "33"}, {"Grw": "W", "RadiusVis": "3000", "Nav": "1", "Hem": "S", "LongMin": "29", "LongMil": "176", "NoWptAsr": "", "Asr": "0", "VitLim": "0", "RadiusWpt": "200", "CodeWpt": "282", "lon": "-64.4862666667", "WPM": "0", "CodeB": "8765", "WPE": "0", "actif": "1", "LatMil": "605", "LatMin": "5", "Tpe": "0", "Tpc": "1", "NomWpt": "K4   ", "LatDeg": "31", "Tps": "0", "lat": "-31.0934166667", "NoWpt": "34", "CP": "1", "NbModif": "2", "LongDeg": "64", "CodeRoute": "138", "VitInter": "0", "Odometre": "4160", "NoWptNav": "34", "radius": "200", "Tri2": "34"}, {"Grw": "W", "RadiusVis": "3000", "Nav": "1", "Hem": "S", "LongMin": "29", "LongMil": "114", "NoWptAsr": "", "Asr": "0", "VitLim": "0", "RadiusWpt": "200", "CodeWpt": "284", "lon": "-64.4852333333", "WPM": "0", "CodeB": "8765", "WPE": "0", "actif": "1", "LatMil": "832", "LatMin": "6", "Tpe": "0", "Tpc": "1", "NomWpt": "K7   ", "LatDeg": "31", "Tps": "0", "lat": "-31.1138666667", "NoWpt": "35", "CP": "1", "NbModif": "2", "LongDeg": "64", "CodeRoute": "138", "VitInter": "0", "Odometre": "7470", "NoWptNav": "35", "radius": "200", "Tri2": "35"}, {"Grw": "W", "RadiusVis": "3000", "Nav": "1", "Hem": "S", "LongMin": "27", "LongMil": "880", "NoWptAsr": "", "Asr": "0", "VitLim": "0", "RadiusWpt": "200", "CodeWpt": "286", "lon": "-64.4646666667", "WPM": "0", "CodeB": "8765", "WPE": "0", "actif": "1", "LatMil": "759", "LatMin": "6", "Tpe": "0", "Tpc": "1", "NomWpt": "K9   ", "LatDeg": "31", "Tps": "0", "lat": "-31.11265", "NoWpt": "36", "CP": "1", "NbModif": "2", "LongDeg": "64", "CodeRoute": "138", "VitInter": "0", "Odometre": "9500", "NoWptNav": "36", "radius": "200", "Tri2": "36"}, {"Grw": "W", "RadiusVis": "3000", "Nav": "1", "Hem": "S", "LongMin": "18", "LongMil": "89", "NoWptAsr": "", "Asr": "0", "VitLim": "0", "RadiusWpt": "200", "CodeWpt": "288", "lon": "-64.3148333333", "WPM": "0", "CodeB": "8765", "WPE": "0", "actif": "1", "LatMil": "630", "LatMin": "9", "Tpe": "0", "Tpc": "1", "NomWpt": "K39  ", "LatDeg": "31", "Tps": "0", "lat": "-31.1605", "NoWpt": "37", "CP": "1", "NbModif": "2", "LongDeg": "64", "CodeRoute": "138", "VitInter": "0", "Odometre": "39730", "NoWptNav": "37", "radius": "200", "Tri2": "37"}, {"Grw": "W", "RadiusVis": "3000", "Nav": "1", "Hem": "S", "LongMin": "14", "LongMil": "991", "NoWptAsr": "", "Asr": "0", "VitLim": "0", "RadiusWpt": "200", "CodeWpt": "290", "lon": "-64.24985", "WPM": "0", "CodeB": "8765", "WPE": "0", "actif": "1", "LatMil": "24", "LatMin": "15", "Tpe": "0", "Tpc": "1", "NomWpt": "K51  ", "LatDeg": "31", "Tps": "0", "lat": "-31.254", "NoWpt": "38", "CP": "1", "NbModif": "2", "LongDeg": "64", "CodeRoute": "138", "VitInter": "0", "Odometre": "51150", "NoWptNav": "38", "radius": "200", "Tri2": "38"}, {"Grw": "W", "RadiusVis": "3000", "Nav": "1", "Hem": "S", "LongMin": "18", "LongMil": "177", "NoWptAsr": "", "Asr": "0", "VitLim": "0", "RadiusWpt": "200", "CodeWpt": "292", "lon": "-64.30295", "WPM": "0", "CodeB": "8765", "WPE": "0", "actif": "1", "LatMil": "911", "LatMin": "15", "Tpe": "0", "Tpc": "1", "NomWpt": "BIV1 ", "LatDeg": "31", "Tps": "0", "lat": "-31.2651833333", "NoWpt": "39", "CP": "1", "NbModif": "2", "LongDeg": "64", "CodeRoute": "138", "VitInter": "0", "Odometre": "0", "NoWptNav": "39", "radius": "200", "Tri2": "39"}, {"Grw": "W", "RadiusVis": "3000", "Nav": "1", "Hem": "S", "LongMin": "18", "LongMil": "177", "NoWptAsr": "", "Asr": "0", "VitLim": "0", "RadiusWpt": "200", "CodeWpt": "294", "lon": "-64.30295", "WPM": "0", "CodeB": "8765", "WPE": "0", "actif": "1", "LatMil": "911", "LatMin": "15", "Tpe": "0", "Tpc": "1", "NomWpt": "E2K0 ", "LatDeg": "31", "Tps": "0", "lat": "-31.2651833333", "NoWpt": "1", "CP": "1", "NbModif": "2", "LongDeg": "64", "CodeRoute": "142", "VitInter": "0", "Odometre": "1", "NoWptNav": "1", "radius": "200", "Tri2": "1"}, {"Grw": "W", "RadiusVis": "3000", "Nav": "1", "Hem": "S", "LongMin": "18", "LongMil": "69", "NoWptAsr": "", "Asr": "0", "VitLim": "0", "RadiusWpt": "200", "CodeWpt": "296", "lon": "-64.3115", "WPM": "0", "CodeB": "8765", "WPE": "0", "actif": "1", "LatMil": "670", "LatMin": "15", "Tpe": "0", "Tpc": "1", "NomWpt": "K0   ", "LatDeg": "31", "Tps": "0", "lat": "-31.2611666667", "NoWpt": "2", "CP": "1", "NbModif": "2", "LongDeg": "64", "CodeRoute": "142", "VitInter": "0", "Odometre": "480", "NoWptNav": "2", "radius": "200", "Tri2": "2"}, {"Grw": "W", "RadiusVis": "3000", "Nav": "1", "Hem": "S", "LongMin": "18", "LongMil": "67", "NoWptAsr": "", "Asr": "0", "VitLim": "0", "RadiusWpt": "200", "CodeWpt": "298", "lon": "-64.3111666667", "WPM": "0", "CodeB": "8765", "WPE": "0", "actif": "1", "LatMil": "664", "LatMin": "9", "Tpe": "0", "Tpc": "1", "NomWpt": "K17  ", "LatDeg": "31", "Tps": "0", "lat": "-31.1610666667", "NoWpt": "3", "CP": "1", "NbModif": "2", "LongDeg": "64", "CodeRoute": "142", "VitInter": "0", "Odometre": "17110", "NoWptNav": "3", "radius": "200", "Tri2": "3"}, {"Grw": "W", "RadiusVis": "3000", "Nav": "1", "Hem": "S", "LongMin": "32", "LongMil": "254", "NoWptAsr": "", "Asr": "0", "VitLim": "0", "RadiusWpt": "200", "CodeWpt": "300", "lon": "-64.5375666667", "WPM": "0", "CodeB": "8765", "WPE": "0", "actif": "1", "LatMil": "523", "LatMin": "47", "Tpe": "0", "Tpc": "1", "NomWpt": "K87  ", "LatDeg": "30", "Tps": "0", "lat": "-30.79205", "NoWpt": "4", "CP": "1", "NbModif": "2", "LongDeg": "64", "CodeRoute": "142", "VitInter": "0", "Odometre": "87710", "NoWptNav": "4", "radius": "200", "Tri2": "4"}, {"Grw": "W", "RadiusVis": "3000", "Nav": "1", "Hem": "S", "LongMin": "31", "LongMil": "876", "NoWptAsr": "", "Asr": "0", "VitLim": "0", "RadiusWpt": "200", "CodeWpt": "302", "lon": "-64.5312666667", "WPM": "0", "CodeB": "8765", "WPE": "0", "actif": "1", "LatMil": "194", "LatMin": "47", "Tpe": "0", "Tpc": "1", "NomWpt": "DSS2 ", "LatDeg": "30", "Tps": "0", "lat": "-30.7865666667", "NoWpt": "5", "CP": "1", "NbModif": "2", "LongDeg": "64", "CodeRoute": "142", "VitInter": "0", "Odometre": "1", "NoWptNav": "5", "radius": "200", "Tri2": "5"}, {"Grw": "W", "RadiusVis": "3000", "Nav": "1", "Hem": "S", "LongMin": "28", "LongMil": "260", "NoWptAsr": "", "Asr": "0", "VitLim": "0", "RadiusWpt": "200", "CodeWpt": "304", "lon": "-64.471", "WPM": "1", "CodeB": "8765", "WPE": "0", "actif": "1", "LatMil": "469", "LatMin": "40", "Tpe": "0", "Tpc": "1", "NomWpt": "K24  ", "LatDeg": "30", "Tps": "0", "lat": "-30.6744833333", "NoWpt": "6", "CP": "1", "NbModif": "2", "LongDeg": "64", "CodeRoute": "142", "VitInter": "0", "Odometre": "24640", "NoWptNav": "6", "radius": "200", "Tri2": "6"}, {"Grw": "W", "RadiusVis": "3000", "Nav": "1", "Hem": "S", "LongMin": "28", "LongMil": "953", "NoWptAsr": "", "Asr": "0", "VitLim": "0", "RadiusWpt": "200", "CodeWpt": "306", "lon": "-64.48255", "WPM": "1", "CodeB": "8765", "WPE": "0", "actif": "1", "LatMil": "559", "LatMin": "40", "Tpe": "0", "Tpc": "1", "NomWpt": "K25  ", "LatDeg": "30", "Tps": "0", "lat": "-30.6759833333", "NoWpt": "7", "CP": "1", "NbModif": "2", "LongDeg": "64", "CodeRoute": "142", "VitInter": "0", "Odometre": "25870", "NoWptNav": "7", "radius": "200", "Tri2": "7"}, {"Grw": "W", "RadiusVis": "3000", "Nav": "1", "Hem": "S", "LongMin": "29", "LongMil": "411", "NoWptAsr": "", "Asr": "0", "VitLim": "0", "RadiusWpt": "90", "CodeWpt": "308", "lon": "-64.4901833333", "WPM": "1", "CodeB": "8765", "WPE": "0", "actif": "1", "LatMil": "704", "LatMin": "38", "Tpe": "0", "Tpc": "1", "NomWpt": "DZ30 ", "LatDeg": "30", "Tps": "0", "lat": "-30.6450666667", "NoWpt": "8", "CP": "1", "NbModif": "2", "LongDeg": "64", "CodeRoute": "142", "VitInter": "30", "Odometre": "30150", "NoWptNav": "8", "radius": "90", "Tri2": "8"}, {"Grw": "W", "RadiusVis": "3000", "Nav": "1", "Hem": "S", "LongMin": "30", "LongMil": "264", "NoWptAsr": "", "Asr": "0", "VitLim": "0", "RadiusWpt": "90", "CodeWpt": "310", "lon": "-64.5044", "WPM": "1", "CodeB": "8765", "WPE": "1", "actif": "1", "LatMil": "652", "LatMin": "38", "Tpe": "0", "Tpc": "1", "NomWpt": "FZ31 ", "LatDeg": "30", "Tps": "0", "lat": "-30.6442", "NoWpt": "9", "CP": "1", "NbModif": "2", "LongDeg": "64", "CodeRoute": "142", "VitInter": "0", "Odometre": "31670", "NoWptNav": "9", "radius": "90", "Tri2": "9"}, {"Grw": "W", "RadiusVis": "3000", "Nav": "1", "Hem": "S", "LongMin": "32", "LongMil": "9", "NoWptAsr": "", "Asr": "0", "VitLim": "0", "RadiusWpt": "200", "CodeWpt": "312", "lon": "-64.5483333333", "WPM": "1", "CodeB": "8765", "WPE": "0", "actif": "1", "LatMil": "797", "LatMin": "37", "Tpe": "0", "Tpc": "1", "NomWpt": "K35  ", "LatDeg": "30", "Tps": "0", "lat": "-30.62995", "NoWpt": "10", "CP": "1", "NbModif": "2", "LongDeg": "64", "CodeRoute": "142", "VitInter": "0", "Odometre": "35810", "NoWptNav": "10", "radius": "200", "Tri2": "10"}, {"Grw": "W", "RadiusVis": "3000", "Nav": "1", "Hem": "S", "LongMin": "32", "LongMil": "814", "NoWptAsr": "", "Asr": "0", "VitLim": "0", "RadiusWpt": "200", "CodeWpt": "314", "lon": "-64.5469", "WPM": "1", "CodeB": "8765", "WPE": "0", "actif": "1", "LatMil": "148", "LatMin": "37", "Tpe": "0", "Tpc": "1", "NomWpt": "CP1  ", "LatDeg": "30", "Tps": "0", "lat": "-30.6191333333", "NoWpt": "11", "CP": "1", "NbModif": "2", "LongDeg": "64", "CodeRoute": "142", "VitInter": "0", "Odometre": "37830", "NoWptNav": "11", "radius": "200", "Tri2": "11"}, {"Grw": "W", "RadiusVis": "3000", "Nav": "1", "Hem": "S", "LongMin": "34", "LongMil": "74", "NoWptAsr": "", "Asr": "0", "VitLim": "0", "RadiusWpt": "200", "CodeWpt": "316", "lon": "-64.579", "WPM": "1", "CodeB": "8765", "WPE": "0", "actif": "1", "LatMil": "764", "LatMin": "35", "Tpe": "0", "Tpc": "1", "NomWpt": "K41  ", "LatDeg": "30", "Tps": "0", "lat": "-30.5960666667", "NoWpt": "12", "CP": "1", "NbModif": "2", "LongDeg": "64", "CodeRoute": "142", "VitInter": "0", "Odometre": "41370", "NoWptNav": "12", "radius": "200", "Tri2": "12"}, {"Grw": "W", "RadiusVis": "3000", "Nav": "1", "Hem": "S", "LongMin": "34", "LongMil": "97", "NoWptAsr": "", "Asr": "0", "VitLim": "0", "RadiusWpt": "200", "CodeWpt": "318", "lon": "-64.5828333333", "WPM": "1", "CodeB": "8765", "WPE": "0", "actif": "1", "LatMil": "148", "LatMin": "35", "Tpe": "0", "Tpc": "1", "NomWpt": "K42  ", "LatDeg": "30", "Tps": "0", "lat": "-30.5858", "NoWpt": "13", "CP": "1", "NbModif": "2", "LongDeg": "64", "CodeRoute": "142", "VitInter": "0", "Odometre": "42900", "NoWptNav": "13", "radius": "200", "Tri2": "13"}, {"Grw": "W", "RadiusVis": "3000", "Nav": "1", "Hem": "S", "LongMin": "33", "LongMil": "345", "NoWptAsr": "", "Asr": "0", "VitLim": "0", "RadiusWpt": "200", "CodeWpt": "320", "lon": "-64.55575", "WPM": "1", "CodeB": "8765", "WPE": "0", "actif": "1", "LatMil": "139", "LatMin": "34", "Tpe": "0", "Tpc": "1", "NomWpt": "K45  ", "LatDeg": "30", "Tps": "0", "lat": "-30.5689833333", "NoWpt": "14", "CP": "1", "NbModif": "2", "LongDeg": "64", "CodeRoute": "142", "VitInter": "0", "Odometre": "45400", "NoWptNav": "14", "radius": "200", "Tri2": "14"}, {"Grw": "W", "RadiusVis": "3000", "Nav": "1", "Hem": "S", "LongMin": "29", "LongMil": "16", "NoWptAsr": "", "Asr": "0", "VitLim": "0", "RadiusWpt": "200", "CodeWpt": "322", "lon": "-64.486", "WPM": "1", "CodeB": "8765", "WPE": "0", "actif": "1", "LatMil": "62", "LatMin": "28", "Tpe": "0", "Tpc": "1", "NomWpt": "K63  ", "LatDeg": "30", "Tps": "0", "lat": "-30.477", "NoWpt": "15", "CP": "1", "NbModif": "2", "LongDeg": "64", "CodeRoute": "142", "VitInter": "0", "Odometre": "63550", "NoWptNav": "15", "radius": "200", "Tri2": "15"}, {"Grw": "W", "RadiusVis": "3000", "Nav": "1", "Hem": "S", "LongMin": "22", "LongMil": "62", "NoWptAsr": "", "Asr": "0", "VitLim": "0", "RadiusWpt": "90", "CodeWpt": "324", "lon": "-64.377", "WPM": "1", "CodeB": "8765", "WPE": "0", "actif": "1", "LatMil": "662", "LatMin": "34", "Tpe": "0", "Tpc": "1", "NomWpt": "DZ86 ", "LatDeg": "30", "Tps": "0", "lat": "-30.5777", "NoWpt": "16", "CP": "1", "NbModif": "2", "LongDeg": "64", "CodeRoute": "142", "VitInter": "30", "Odometre": "86740", "NoWptNav": "16", "radius": "90", "Tri2": "16"}, {"Grw": "W", "RadiusVis": "3000", "Nav": "1", "Hem": "S", "LongMin": "21", "LongMil": "672", "NoWptAsr": "", "Asr": "0", "VitLim": "0", "RadiusWpt": "90", "CodeWpt": "326", "lon": "-64.3612", "WPM": "1", "CodeB": "8765", "WPE": "1", "actif": "1", "LatMil": "906", "LatMin": "34", "Tpe": "0", "Tpc": "1", "NomWpt": "FZ87 ", "LatDeg": "30", "Tps": "0", "lat": "-30.5817666667", "NoWpt": "17", "CP": "1", "NbModif": "2", "LongDeg": "64", "CodeRoute": "142", "VitInter": "0", "Odometre": "87550", "NoWptNav": "17", "radius": "90", "Tri2": "17"}, {"Grw": "W", "RadiusVis": "3000", "Nav": "1", "Hem": "S", "LongMin": "19", "LongMil": "21", "NoWptAsr": "", "Asr": "0", "VitLim": "0", "RadiusWpt": "90", "CodeWpt": "328", "lon": "-64.3201666667", "WPM": "1", "CodeB": "8765", "WPE": "0", "actif": "1", "LatMil": "372", "LatMin": "41", "Tpe": "0", "Tpc": "1", "NomWpt": "DZ102", "LatDeg": "30", "Tps": "0", "lat": "-30.6895333333", "NoWpt": "18", "CP": "1", "NbModif": "2", "LongDeg": "64", "CodeRoute": "142", "VitInter": "30", "Odometre": "102100", "NoWptNav": "18", "radius": "90", "Tri2": "18"}, {"Grw": "W", "RadiusVis": "3000", "Nav": "1", "Hem": "S", "LongMin": "17", "LongMil": "663", "NoWptAsr": "", "Asr": "0", "VitLim": "0", "RadiusWpt": "90", "CodeWpt": "330", "lon": "-64.2943833333", "WPM": "1", "CodeB": "8765", "WPE": "1", "actif": "1", "LatMil": "725", "LatMin": "41", "Tpe": "0", "Tpc": "1", "NomWpt": "FZ104", "LatDeg": "30", "Tps": "0", "lat": "-30.6954166667", "NoWpt": "19", "CP": "1", "NbModif": "2", "LongDeg": "64", "CodeRoute": "142", "VitInter": "0", "Odometre": "104650", "NoWptNav": "19", "radius": "90", "Tri2": "19"}, {"Grw": "W", "RadiusVis": "3000", "Nav": "1", "Hem": "S", "LongMin": "16", "LongMil": "578", "NoWptAsr": "", "Asr": "0", "VitLim": "0", "RadiusWpt": "200", "CodeWpt": "332", "lon": "-64.2763", "WPM": "1", "CodeB": "8765", "WPE": "0", "actif": "1", "LatMil": "797", "LatMin": "46", "Tpe": "0", "Tpc": "1", "NomWpt": "K123 ", "LatDeg": "30", "Tps": "0", "lat": "-30.77995", "NoWpt": "20", "CP": "1", "NbModif": "2", "LongDeg": "64", "CodeRoute": "142", "VitInter": "0", "Odometre": "123840", "NoWptNav": "20", "radius": "200", "Tri2": "20"}, {"Grw": "W", "RadiusVis": "3000", "Nav": "1", "Hem": "S", "LongMin": "16", "LongMil": "439", "NoWptAsr": "", "Asr": "0", "VitLim": "0", "RadiusWpt": "90", "CodeWpt": "334", "lon": "-64.2739833333", "WPM": "1", "CodeB": "8765", "WPE": "0", "actif": "1", "LatMil": "919", "LatMin": "50", "Tpe": "0", "Tpc": "1", "NomWpt": "DZ137", "LatDeg": "30", "Tps": "0", "lat": "-30.84865", "NoWpt": "21", "CP": "1", "NbModif": "2", "LongDeg": "64", "CodeRoute": "142", "VitInter": "30", "Odometre": "137050", "NoWptNav": "21", "radius": "90", "Tri2": "21"}, {"Grw": "W", "RadiusVis": "3000", "Nav": "1", "Hem": "S", "LongMin": "16", "LongMil": "649", "NoWptAsr": "", "Asr": "0", "VitLim": "0", "RadiusWpt": "90", "CodeWpt": "336", "lon": "-64.2774833333", "WPM": "1", "CodeB": "8765", "WPE": "1", "actif": "1", "LatMil": "141", "LatMin": "51", "Tpe": "0", "Tpc": "1", "NomWpt": "FZ138", "LatDeg": "30", "Tps": "0", "lat": "-30.85235", "NoWpt": "22", "CP": "1", "NbModif": "2", "LongDeg": "64", "CodeRoute": "142", "VitInter": "0", "Odometre": "138030", "NoWptNav": "22", "radius": "90", "Tri2": "22"}, {"Grw": "W", "RadiusVis": "3000", "Nav": "1", "Hem": "S", "LongMin": "20", "LongMil": "667", "NoWptAsr": "", "Asr": "0", "VitLim": "0", "RadiusWpt": "90", "CodeWpt": "338", "lon": "-64.34445", "WPM": "1", "CodeB": "8765", "WPE": "0", "actif": "1", "LatMil": "66", "LatMin": "53", "Tpe": "0", "Tpc": "1", "NomWpt": "DZ149", "LatDeg": "30", "Tps": "0", "lat": "-30.8943333333", "NoWpt": "23", "CP": "1", "NbModif": "2", "LongDeg": "64", "CodeRoute": "142", "VitInter": "30", "Odometre": "149170", "NoWptNav": "23", "radius": "90", "Tri2": "23"}, {"Grw": "W", "RadiusVis": "3000", "Nav": "1", "Hem": "S", "LongMin": "20", "LongMil": "345", "NoWptAsr": "", "Asr": "0", "VitLim": "0", "RadiusWpt": "90", "CodeWpt": "340", "lon": "-64.3390833333", "WPM": "1", "CodeB": "8765", "WPE": "1", "actif": "1", "LatMil": "381", "LatMin": "53", "Tpe": "0", "Tpc": "1", "NomWpt": "FZ150", "LatDeg": "30", "Tps": "0", "lat": "-30.8896833333", "NoWpt": "24", "CP": "1", "NbModif": "2", "LongDeg": "64", "CodeRoute": "142", "VitInter": "0", "Odometre": "150140", "NoWptNav": "24", "radius": "90", "Tri2": "24"}, {"Grw": "W", "RadiusVis": "3000", "Nav": "1", "Hem": "S", "LongMin": "16", "LongMil": "243", "NoWptAsr": "", "Asr": "0", "VitLim": "0", "RadiusWpt": "200", "CodeWpt": "342", "lon": "-64.2707166667", "WPM": "0", "CodeB": "8765", "WPE": "0", "actif": "1", "LatMil": "390", "LatMin": "56", "Tpe": "0", "Tpc": "1", "NomWpt": "ASS2 ", "LatDeg": "30", "Tps": "0", "lat": "-30.9398333333", "NoWpt": "25", "CP": "1", "NbModif": "2", "LongDeg": "64", "CodeRoute": "142", "VitInter": "0", "Odometre": "1", "NoWptNav": "25", "radius": "200", "Tri2": "25"}, {"Grw": "W", "RadiusVis": "3000", "Nav": "1", "Hem": "S", "LongMin": "15", "LongMil": "723", "NoWptAsr": "", "Asr": "0", "VitLim": "0", "RadiusWpt": "200", "CodeWpt": "344", "lon": "-64.26205", "WPM": "0", "CodeB": "8765", "WPE": "0", "actif": "1", "LatMil": "443", "LatMin": "57", "Tpe": "0", "Tpc": "1", "NomWpt": "K2   ", "LatDeg": "30", "Tps": "0", "lat": "-30.9573833333", "NoWpt": "26", "CP": "1", "NbModif": "2", "LongDeg": "64", "CodeRoute": "142", "VitInter": "0", "Odometre": "2170", "NoWptNav": "26", "radius": "200", "Tri2": "26"}, {"Grw": "W", "RadiusVis": "3000", "Nav": "1", "Hem": "S", "LongMin": "14", "LongMil": "980", "NoWptAsr": "", "Asr": "0", "VitLim": "0", "RadiusWpt": "200", "CodeWpt": "346", "lon": "-64.2496666667", "WPM": "0", "CodeB": "8765", "WPE": "0", "actif": "1", "LatMil": "28", "LatMin": "15", "Tpe": "0", "Tpc": "1", "NomWpt": "K40  ", "LatDeg": "31", "Tps": "0", "lat": "-31.2546666667", "NoWpt": "27", "CP": "1", "NbModif": "2", "LongDeg": "64", "CodeRoute": "142", "VitInter": "0", "Odometre": "40120", "NoWptNav": "27", "radius": "200", "Tri2": "27"}, {"Grw": "W", "RadiusVis": "3000", "Nav": "1", "Hem": "S", "LongMin": "18", "LongMil": "65", "NoWptAsr": "", "Asr": "0", "VitLim": "0", "RadiusWpt": "200", "CodeWpt": "348", "lon": "-64.3108333333", "WPM": "0", "CodeB": "8765", "WPE": "0", "actif": "1", "LatMil": "656", "LatMin": "15", "Tpe": "0", "Tpc": "1", "NomWpt": "K45  ", "LatDeg": "31", "Tps": "0", "lat": "-31.2609333333", "NoWpt": "28", "CP": "1", "NbModif": "2", "LongDeg": "64", "CodeRoute": "142", "VitInter": "0", "Odometre": "45230", "NoWptNav": "28", "radius": "200", "Tri2": "28"}, {"Grw": "W", "RadiusVis": "3000", "Nav": "1", "Hem": "S", "LongMin": "18", "LongMil": "177", "NoWptAsr": "", "Asr": "0", "VitLim": "0", "RadiusWpt": "200", "CodeWpt": "350", "lon": "-64.30295", "WPM": "0", "CodeB": "8765", "WPE": "0", "actif": "1", "LatMil": "911", "LatMin": "15", "Tpe": "0", "Tpc": "1", "NomWpt": "BIV2 ", "LatDeg": "31", "Tps": "0", "lat": "-31.2651833333", "NoWpt": "29", "CP": "1", "NbModif": "2", "LongDeg": "64", "CodeRoute": "142", "VitInter": "0", "Odometre": "0", "NoWptNav": "29", "radius": "200", "Tri2": "29"}, {"Grw": "E", "RadiusVis": "3000", "Nav": "1", "Hem": "N", "LongMin": "0", "LongMil": "0", "NoWptAsr": "", "Asr": "0", "VitLim": "0", "RadiusWpt": "200", "CodeWpt": "572", "lon": "-0.0", "WPM": "0", "CodeB": "8765", "WPE": "0", "actif": "1", "LatMil": "0", "LatMin": "0", "Tpe": "0", "Tpc": "1", "NomWpt": "V1MEN", "LatDeg": "0", "Tps": "0", "lat": "-0.0", "NoWpt": "1", "CP": "1", "NbModif": "2", "LongDeg": "0", "CodeRoute": "254", "VitInter": "0", "Odometre": "0", "NoWptNav": "1", "radius": "200", "Tri2": "1"}, {"Grw": "E", "RadiusVis": "3000", "Nav": "1", "Hem": "N", "LongMin": "0", "LongMil": "0", "NoWptAsr": "", "Asr": "0", "VitLim": "0", "RadiusWpt": "200", "CodeWpt": "581", "lon": "-0.0", "WPM": "0", "CodeB": "8765", "WPE": "0", "actif": "1", "LatMil": "0", "LatMin": "0", "Tpe": "0", "Tpc": "1", "NomWpt": "AUTO ", "LatDeg": "0", "Tps": "0", "lat": "-0.0", "NoWpt": "2", "CP": "1", "NbModif": "2", "LongDeg": "0", "CodeRoute": "254", "VitInter": "0", "Odometre": "0", "NoWptNav": "2", "radius": "200", "Tri2": "2"}]